{"Records":[{"eventVersion":"1.08","userIdentity":{"type":"AWSService","invokedBy":"rds.amazonaws.com"},"eventTime":"2022-04-18T13:49:42Z","eventSource":"kms.amazonaws.com","eventName":"GenerateDataKey","awsRegion":"us-west-1","sourceIPAddress":"rds.amazonaws.com","userAgent":"rds.amazonaws.com","requestParameters":{"encryptionContext":{"aws:rds:db-id":"db-ZFYZUY2EMRVEWKKQHIYYAIL2IY"},"keyId":"arn:aws:kms:us-west-1:479841282623:key/d36ef428-49b5-47ea-a063-0454c4b0ec9b","numberOfBytes":32},"responseElements":null,"requestID":"2a02146f-c8fb-4ec1-875a-67c93841649f","eventID":"0c28d05e-24ac-4c96-8ff2-a5390ea1f104","readOnly":true,"resources":[{"accountId":"479841282623","type":"AWS::KMS::Key","ARN":"arn:aws:kms:us-west-1:479841282623:key/d36ef428-49b5-47ea-a063-0454c4b0ec9b"}],"eventType":"AwsApiCall","managementEvent":true,"recipientAccountId":"479841282623","sharedEventID":"77d2a293-6e78-4b14-8846-06d6702da00a","eventCategory":"Management"},{"eventVersion":"1.08","userIdentity":{"type":"AWSService","invokedBy":"rds.amazonaws.com"},"eventTime":"2022-04-18T13:53:42Z","eventSource":"kms.amazonaws.com","eventName":"GenerateDataKey","awsRegion":"us-west-1","sourceIPAddress":"rds.amazonaws.com","userAgent":"rds.amazonaws.com","requestParameters":{"encryptionContext":{"aws:rds:db-id":"db-ZFYZUY2EMRVEWKKQHIYYAIL2IY"},"keyId":"arn:aws:kms:us-west-1:479841282623:key/d36ef428-49b5-47ea-a063-0454c4b0ec9b","numberOfBytes":32},"responseElements":null,"requestID":"c9c1d130-2662-4cbe-bc8e-4d21c3292140","eventID":"e51751b4-b1ec-4c8b-aac7-056691b04500","readOnly":true,"resources":[{"accountId":"479841282623","type":"AWS::KMS::Key","ARN":"arn:aws:kms:us-west-1:479841282623:key/d36ef428-49b5-47ea-a063-0454c4b0ec9b"}],"eventType":"AwsApiCall","managementEvent":true,"recipientAccountId":"479841282623","sharedEventID":"a7c027a0-ba37-435c-98ad-0614497acf00","eventCategory":"Management"}]}